pyterrier_alpha/__init__.py
pyterrier_alpha/artifact.py
pyterrier_alpha/dataframe_builder.py
pyterrier_alpha/fusion.py
pyterrier_alpha/inspect.py
pyterrier_alpha/io.py
pyterrier_alpha/parallel.py
pyterrier_alpha/rbo.py
pyterrier_alpha/transform.py
pyterrier_alpha/transformer_repr.py
pyterrier_alpha/utils.py
pyterrier_alpha/validate.py
pyterrier_alpha/pt_docs/dataframe_builder.rst
pyterrier_alpha/pt_docs/fusion.rst
pyterrier_alpha/pt_docs/index.rst
pyterrier_alpha/pt_docs/inspect.rst
pyterrier_alpha/pt_docs/parallel.rst
pyterrier_alpha/pt_docs/rbo.rst
pyterrier_alpha/pt_docs/transform.rst
pyterrier_alpha/pt_docs/utils.rst
pyterrier_alpha/pt_docs/validate.rst
pyterrier_alpha-0.16.4.dist-info/licenses/LICENSE
pyterrier_alpha-0.16.4.dist-info/METADATA
pyterrier_alpha-0.16.4.dist-info/WHEEL
pyterrier_alpha-0.16.4.dist-info/top_level.txt
pyterrier_alpha-0.16.4.dist-info/RECORD
