Metadata-Version: 2.4
Name: pyterrier-alpha
Version: 0.16.4
Summary: Alpha channel of features for PyTerrier
Author-email: Sean MacAvaney <sean.macavaney@glasgow.ac.uk>
Maintainer-email: Sean MacAvaney <sean.macavaney@glasgow.ac.uk>
Project-URL: Repository, https://github.com/seanmacavaney/pyterrier-alpha
Project-URL: Bug Tracker, https://github.com/seanmacavaney/pyterrier-alpha/issues
Classifier: Programming Language :: Python
Classifier: Operating System :: OS Independent
Classifier: Topic :: Text Processing
Classifier: Topic :: Text Processing :: Indexing
Classifier: License :: OSI Approved :: MIT License
Requires-Python: >=3.6
License-File: LICENSE
Requires-Dist: python-terrier>=0.13.0
Provides-Extra: parallel
Requires-Dist: joblib; extra == "parallel"
Dynamic: license-file
